LICENSE.txt
MANIFEST.in
README.md
README.rst
setup.py
baseclasses/__init__.py
baseclasses/_version.py
baseclasses/admin.py
baseclasses/fields.py
baseclasses/models.py
django_baseclasses.egg-info/PKG-INFO
django_baseclasses.egg-info/SOURCES.txt
django_baseclasses.egg-info/dependency_links.txt
django_baseclasses.egg-info/not-zip-safe
django_baseclasses.egg-info/requires.txt
django_baseclasses.egg-info/top_level.txt