Metadata-Version: 1.1
Name: django-baseclasses
Version: 1.0.9
Summary: A set of reusable base classes and helpers for django
Home-page: https://github.com/gregplaysguitar/django-baseclasses
Author: Greg Brown
Author-email: greg@gregbrown.co.nz
License: UNKNOWN
Platform: any
Classifier: Development Status :: 5 - Production/Stable
Classifier: Environment :: Web Environment
Classifier: Intended Audience :: Developers
Classifier: Operating System :: OS Independent
Classifier: Programming Language :: Python
Classifier: Topic :: Internet :: WWW/HTTP :: Dynamic Content
Classifier: Framework :: Django
